mindocr/__init__.py
mindocr/version.py
mindocr/data/__init__.py
mindocr/data/base_dataset.py
mindocr/data/builder.py
mindocr/data/constants.py
mindocr/data/det_dataset.py
mindocr/data/kie_dataset.py
mindocr/data/layout_dataset.py
mindocr/data/predict_dataset.py
mindocr/data/rec_dataset.py
mindocr/data/rec_lmdb_dataset.py
mindocr/data/table_pubtab_dataset.py
mindocr/data/transforms/__init__.py
mindocr/data/transforms/det_east_transforms.py
mindocr/data/transforms/det_transforms.py
mindocr/data/transforms/general_transforms.py
mindocr/data/transforms/layoutlm_transforms.py
mindocr/data/transforms/llm_transform.py
mindocr/data/transforms/rec_abinet_transforms.py
mindocr/data/transforms/rec_transforms.py
mindocr/data/transforms/svtr_transform.py
mindocr/data/transforms/table_transform.py
mindocr/data/transforms/transforms_factory.py
mindocr/data/utils/polygon_utils.py
mindocr/losses/__init__.py
mindocr/losses/abinet_loss.py
mindocr/losses/builder.py
mindocr/losses/cls_loss.py
mindocr/losses/det_loss.py
mindocr/losses/kie_loss.py
mindocr/losses/rec_loss.py
mindocr/losses/rec_multi_loss.py
mindocr/losses/table_master_loss.py
mindocr/losses/yolov8_loss.py
mindocr/metrics/__init__.py
mindocr/metrics/builder.py
mindocr/metrics/cls_metrics.py
mindocr/metrics/det_metrics.py
mindocr/metrics/kie_metrics.py
mindocr/metrics/layout_metrics.py
mindocr/metrics/rec_metrics.py
mindocr/metrics/table_metrics.py
mindocr/models/__init__.py
mindocr/models/_registry.py
mindocr/models/base_model.py
mindocr/models/builder.py
mindocr/models/cls_mv3.py
mindocr/models/det_dbnet.py
mindocr/models/det_east.py
mindocr/models/det_psenet.py
mindocr/models/kie_layoutxlm.py
mindocr/models/label_assignment.py
mindocr/models/layout_yolov8.py
mindocr/models/rec_abinet.py
mindocr/models/rec_crnn.py
mindocr/models/rec_master.py
mindocr/models/rec_rare.py
mindocr/models/rec_robustscanner.py
mindocr/models/rec_svtr.py
mindocr/models/rec_visionlan.py
mindocr/models/table_master.py
mindocr-0.5.0.dist-info/licenses/LICENSE
mindocr-0.5.0.dist-info/METADATA
mindocr-0.5.0.dist-info/WHEEL
mindocr-0.5.0.dist-info/top_level.txt
mindocr-0.5.0.dist-info/RECORD
